bioscreen/__init__.py
bioscreen/py.typed
bioscreen/screening.py
bioscreen-0.1.0.dist-info/licenses/LICENSE
bioscreen-0.1.0.dist-info/METADATA
bioscreen-0.1.0.dist-info/WHEEL
bioscreen-0.1.0.dist-info/top_level.txt
bioscreen-0.1.0.dist-info/RECORD
