Metadata-Version: 2.4
Name: bioscreen
Version: 0.1.0
Summary: A biosecurity screening library for AI protein design tools
Author-email: Phillip Palmer <pp502@cam.ac.uk>
License: MIT
Project-URL: Homepage, https://github.com/PhilPalmer/bioscreen
Project-URL: Repository, https://github.com/PhilPalmer/bioscreen
Project-URL: Issues, https://github.com/PhilPalmer/bioscreen/issues
Keywords: biosecurity,protein,screening,ai-safety
Classifier: Development Status :: 3 - Alpha
Classifier: Intended Audience :: Science/Research
Classifier: Intended Audience :: Developers
Classifier: License :: OSI Approved :: MIT License
Classifier: Programming Language :: Python :: 3
Classifier: Programming Language :: Python :: 3.9
Classifier: Programming Language :: Python :: 3.10
Classifier: Programming Language :: Python :: 3.11
Classifier: Programming Language :: Python :: 3.12
Classifier: Topic :: Scientific/Engineering :: Bio-Informatics
Classifier: Topic :: Security
Requires-Python: >=3.9
License-File: LICENSE
Provides-Extra: dev
Requires-Dist: pytest>=7.4.0; extra == "dev"
Requires-Dist: pytest-cov>=4.1.0; extra == "dev"
Requires-Dist: black>=23.7.0; extra == "dev"
Requires-Dist: ruff>=0.0.285; extra == "dev"
Requires-Dist: mypy>=1.5.0; extra == "dev"
Dynamic: license-file
